{"stats":{"minecraft:killed":{"minecraft:zombie_villager":1,"minecraft:iron_golem":3,"minecraft:skeleton":1,"minecraft:drowned":1,"minecraft:villager":2,"minecraft:cow":1},"minecraft:dropped":{"minecraft:enchanted_book":9,"minecraft:iron_ingot":5,"minecraft:netherite_helmet":1,"minecraft:netherite_chestplate":1,"minecraft:grass_block":1,"minecraft:netherite_leggings":1,"minecraft:ice":1,"minecraft:netherite_boots":1},"minecraft:used":{"minecraft:oak_fence":2,"minecraft:netherite_sword":184,"minecraft:trident":14,"minecraft:water_bucket":17,"minecraft:jack_o_lantern":2,"minecraft:cow_spawn_egg":38,"minecraft:flint_and_steel":7,"minecraft:carved_pumpkin":4,"minecraft:prismarine":4,"minecraft:ender_pearl":4,"minecraft:chest":4,"minecraft:shield":2,"minecraft:stone":702,"minecraft:zombie_spawn_egg":5,"minecraft:gold_ore":5,"minecraft:conduit":5,"minecraft:respawn_anchor":13,"minecraft:dragon_egg":3,"minecraft:dirt":1,"minecraft:spyglass":46,"minecraft:anvil":2,"minecraft:tnt":9,"minecraft:hopper":37,"minecraft:birch_sign":81,"minecraft:black_banner":1,"minecraft:blue_ice":40,"minecraft:redstone_torch":16,"minecraft:creeper_spawn_egg":1,"minecraft:sticky_piston":26,"minecraft:glass":116,"minecraft:piston":1,"minecraft:lava_bucket":40,"minecraft:diamond_shovel":1,"minecraft:crying_obsidian":1,"minecraft:villager_spawn_egg":4,"minecraft:iron_block":13,"minecraft:grass_block":17,"minecraft:netherite_axe":28,"minecraft:quartz_block":1,"minecraft:spawner":50,"minecraft:iron_door":1,"minecraft:diamond_sword":28,"minecraft:glowstone":2,"minecraft:repeater":10,"minecraft:bow":10,"minecraft:black_stained_glass":6,"minecraft:bucket":10,"minecraft:ice":143,"minecraft:stone_pressure_plate":10,"minecraft:cooked_beef":3,"minecraft:enchanted_golden_apple":3,"minecraft:gray_stained_glass":6},"minecraft:killed_by":{"minecraft:player":4},"minecraft:mined":{"minecraft:crimson_fence_gate":2,"minecraft:grass_block":1,"minecraft:fire":1,"minecraft:grass":4},"minecraft:picked_up":{"minecraft:feather":2,"minecraft:netherite_boots":5,"minecraft:chicken":1,"minecraft:azure_bluet":2,"minecraft:cooked_beef":70,"minecraft:repeater":1,"minecraft:iron_door":1,"minecraft:leather":4,"minecraft:enchanted_book":16,"minecraft:shield":2,"minecraft:netherite_leggings":4,"minecraft:dirt":1,"minecraft:bow":1,"minecraft:gold_nugget":2,"minecraft:wheat_seeds":2,"minecraft:netherite_sword":4,"minecraft:iron_ingot":10,"minecraft:redstone_torch":6,"minecraft:netherite_axe":2,"minecraft:enchanted_golden_apple":61,"minecraft:cooked_porkchop":64,"minecraft:grass_block":1,"minecraft:spectral_arrow":59,"minecraft:dragon_egg":3,"minecraft:rotten_flesh":2,"minecraft:netherite_helmet":5,"minecraft:birch_sign":5,"minecraft:black_banner":1,"minecraft:netherite_chestplate":4},"minecraft:custom":{"minecraft:mob_kills":12,"minecraft:interact_with_anvil":4,"minecraft:inspect_hopper":5,"minecraft:open_shulker_box":4,"minecraft:leave_game":3,"minecraft:time_since_death":614,"minecraft:climb_one_cm":3024,"minecraft:damage_resisted":78,"minecraft:time_since_rest":645,"minecraft:walk_one_cm":249953,"minecraft:sprint_one_cm":127699,"minecraft:open_enderchest":3,"minecraft:damage_taken":2131,"minecraft:damage_absorbed":164,"minecraft:damage_blocked_by_shield":250,"minecraft:trigger_trapped_chest":7,"minecraft:drop":20,"minecraft:damage_dealt":4559,"minecraft:swim_one_cm":1582,"minecraft:fly_one_cm":1026323,"minecraft:open_chest":18,"minecraft:crouch_one_cm":7982,"minecraft:play_time":115449,"minecraft:deaths":8,"minecraft:sneak_time":3123,"minecraft:walk_under_water_one_cm":67442,"minecraft:boat_one_cm":66219,"minecraft:jump":743,"minecraft:walk_on_water_one_cm":33635,"minecraft:total_world_time":31487,"minecraft:fall_one_cm":12940}},"DataVersion":2724}