{"stats":{"minecraft:dropped":{"minecraft:water_bucket":2,"minecraft:dark_oak_door":2,"minecraft:stripped_spruce_log":1,"minecraft:kelp":29,"minecraft:cooked_beef":4,"minecraft:smooth_quartz_stairs":1,"minecraft:minecart":1,"minecraft:lantern":1,"minecraft:black_bed":1,"minecraft:leather":5,"minecraft:glowstone_dust":2,"minecraft:light_gray_concrete":1,"minecraft:spruce_stairs":1,"minecraft:stick":1,"minecraft:spruce_planks":1,"minecraft:smooth_quartz":1,"minecraft:ladder":1,"minecraft:redstone_torch":1,"minecraft:barrel":1,"minecraft:spruce_slab":1,"minecraft:powered_rail":1,"minecraft:redstone":2},"minecraft:killed":{"minecraft:witch":1,"minecraft:spider":5,"minecraft:creeper":10,"minecraft:squid":1,"minecraft:sheep":2,"minecraft:skeleton":4,"minecraft:zombie":7,"minecraft:ghast":1,"minecraft:cow":4},"minecraft:picked_up":{"minecraft:cocoa_beans":1,"minecraft:cooked_beef":4,"minecraft:flower_pot":1,"minecraft:andesite":2,"minecraft:leather":7,"minecraft:diamond_sword":1,"minecraft:gunpowder":31,"minecraft:string":16,"minecraft:dirt":1,"minecraft:cooked_mutton":7,"minecraft:armor_stand":1,"minecraft:bone":24,"minecraft:kelp":29,"minecraft:wheat_seeds":1,"minecraft:netherite_sword":2,"minecraft:bucket":1,"minecraft:beef":12,"minecraft:minecart":1,"minecraft:glass_bottle":4,"minecraft:glowstone_dust":2,"minecraft:dark_oak_door":1,"minecraft:torch":9,"minecraft:white_bed":3,"minecraft:redstone":2,"minecraft:spider_eye":8,"minecraft:iron_horse_armor":3,"minecraft:arrow":16,"minecraft:rotten_flesh":14,"minecraft:glowstone":1,"minecraft:black_banner":1,"minecraft:dark_oak_fence":1,"minecraft:white_wool":2},"minecraft:mined":{"minecraft:grass_block":1,"minecraft:wall_torch":1},"minecraft:custom":{"minecraft:interact_with_furnace":2,"minecraft:mob_kills":36,"minecraft:open_barrel":3,"minecraft:play_one_minute":228437,"minecraft:pot_flower":9,"minecraft:interact_with_stonecutter":2,"minecraft:leave_game":15,"minecraft:time_since_death":7869,"minecraft:climb_one_cm":13895,"minecraft:time_since_rest":7889,"minecraft:sprint_one_cm":242878,"minecraft:open_enderchest":1,"minecraft:damage_taken":568,"minecraft:walk_one_cm":307134,"minecraft:drop":61,"minecraft:damage_dealt":5275,"minecraft:minecart_one_cm":120363,"minecraft:swim_one_cm":26581,"minecraft:fly_one_cm":1365092,"minecraft:open_chest":32,"minecraft:pig_one_cm":6020,"minecraft:crouch_one_cm":2012,"minecraft:deaths":2,"minecraft:sneak_time":3321,"minecraft:walk_under_water_one_cm":328354,"minecraft:jump":1013,"minecraft:interact_with_blast_furnace":4,"minecraft:walk_on_water_one_cm":60284,"minecraft:interact_with_smoker":1,"minecraft:fall_one_cm":6600},"minecraft:killed_by":{"minecraft:player":2},"minecraft:used":{"minecraft:water_bucket":21,"minecraft:wither_skeleton_skull":1,"minecraft:spruce_slab":23,"minecraft:armor_stand":2,"minecraft:powered_rail":2,"minecraft:polished_andesite":25,"minecraft:gray_carpet":12,"minecraft:ladder":9,"minecraft:light_gray_carpet":2,"minecraft:chest":1,"minecraft:spruce_planks":169,"minecraft:ender_chest":1,"minecraft:stone":55,"minecraft:rotten_flesh":4,"minecraft:smooth_quartz_stairs":57,"minecraft:oak_leaves":9,"minecraft:torch":45,"minecraft:crafting_table":1,"minecraft:spruce_stairs":6,"minecraft:white_bed":33,"minecraft:sponge":16,"minecraft:black_bed":1,"minecraft:painting":5,"minecraft:smoker":1,"minecraft:stripped_spruce_log":68,"minecraft:dark_oak_door":2,"minecraft:redstone_torch":2,"minecraft:flower_pot":8,"minecraft:sea_lantern":6,"minecraft:light_gray_concrete":160,"minecraft:iron_block":964,"minecraft:gray_stained_glass_pane":43,"minecraft:zombie_head":2,"minecraft:heavy_weighted_pressure_plate":2,"minecraft:lantern":2,"minecraft:stone_button":1,"minecraft:warped_nylium":4,"minecraft:smooth_quartz":44,"minecraft:barrel":11,"minecraft:crimson_nylium":4,"minecraft:diamond_sword":66,"minecraft:glowstone":19,"minecraft:crimson_fungus":4,"minecraft:warped_fungus":4,"minecraft:iron_trapdoor":1,"minecraft:furnace":1,"minecraft:dark_oak_fence":6,"minecraft:minecart":7,"minecraft:bucket":7,"minecraft:skeleton_skull":1,"minecraft:gray_banner":4,"minecraft:bone_meal":11}},"DataVersion":2584}